[
  {
    "id": "EACCFEEA-FFB5-45B6-A0D2-EE239222839C",
    "upstreamPerson": "tom@gbera.netos",
    "sourceSite": "",
    "sourceApp": "",
    "onChannel": "3FD24493-4BB4-43C6-A731-FF00375EDA9F",
    "creator": "tom@gbera.netos",
    "ctime": 1578314804000,
    "digests": "2019年12月31日下午，兴义市人民法院公开开庭对毕节市司法局原党组书记、局长张玉梅涉嫌犯受贿罪案进行一审宣判。被告人张玉梅犯受贿罪，判处有期徒刑五年零六个月，并处罚金人民币三十五万元",
    "wy": 7372.3233888383
  },
  {
    "id": "A3658E40-A3D8-4999-ADE0-3420E7F84308",
    "upstreamPerson": "tom@gbera.netos",
    "sourceSite": "",
    "sourceApp": "",
    "onChannel": "3FD24493-4BB4-43C6-A731-FF00375EDA9F",
    "creator": "tom@gbera.netos",
    "ctime": 1578314775000,
    "digests": "论主持人的自我修养！精致康康在线辟谣：每天捯饬得很正经，一进演播室就进入职业状态，从不穿“毛裤”。撒贝宁：我来证明！穿“毛裤”的是小尼！",
    "wy": 8473.958573
  }
]